gamest_plugins/discord_notification_service/__init__.py
gamest_plugins/discord_notification_service/module.py
gamest_discord_notification_service-2.0.4.dist-info/COPYING
gamest_discord_notification_service-2.0.4.dist-info/METADATA
gamest_discord_notification_service-2.0.4.dist-info/WHEEL
gamest_discord_notification_service-2.0.4.dist-info/top_level.txt
gamest_discord_notification_service-2.0.4.dist-info/RECORD
