Metadata-Version: 2.1
Name: gamest-discord-notification-service
Version: 2.0.4
Summary: Send notifications to a discord webhook.
Home-page: https://github.com/sopoforic/gamest_discord_notification_service
Author: Tracy Poff
Author-email: tracy.poff@gmail.com
License: UNKNOWN
Platform: UNKNOWN
Classifier: Development Status :: 4 - Beta
Classifier: Environment :: Win32 (MS Windows)
Classifier: Intended Audience :: End Users/Desktop
Classifier: License :: OSI Approved :: GNU General Public License v3 or later (GPLv3+)
Classifier: Programming Language :: Python :: 3
Classifier: Topic :: Games/Entertainment
